[{"court": "\u5c71\u897f\u7701\u9ad8\u7ea7\u4eba\u6c11\u6cd5\u9662", "province": "\u5c71\u897f", "region": "", "leval": "2", "key": "001004000"}, {"court": "\u5c71\u897f\u7701\u592a\u539f\u5e02\u4e2d\u7ea7\u4eba\u6c11\u6cd5\u9662", "province": "\u5c71\u897f", "region": "\u592a\u539f\u5e02", "leval": "3", "key": "001004001000"}, {"court": "\u5c71\u897f\u7701\u5927\u540c\u5e02\u4e2d\u7ea7\u4eba\u6c11\u6cd5\u9662", "province": "\u5c71\u897f", "region": "\u5927\u540c\u5e02", "leval": "3", "key": "001004002000"}, {"court": "\u5c71\u897f\u7701\u9633\u6cc9\u5e02\u4e2d\u7ea7\u4eba\u6c11\u6cd5\u9662", "province": "\u5c71\u897f", "region": "\u9633\u6cc9\u5e02", "leval": "3", "key": "001004003000"}, {"court": "\u5c71\u897f\u7701\u957f\u6cbb\u5e02\u4e2d\u7ea7\u4eba\u6c11\u6cd5\u9662", "province": "\u5c71\u897f", "region": "\u957f\u6cbb\u5e02", "leval": "3", "key": "001004004000"}, {"court": "\u5c71\u897f\u7701\u664b\u57ce\u5e02\u4e2d\u7ea7\u4eba\u6c11\u6cd5\u9662", "province": "\u5c71\u897f", "region": "\u664b\u57ce\u5e02", "leval": "3", "key": "001004005000"}, {"court": "\u5c71\u897f\u7701\u6714\u5dde\u5e02\u4e2d\u7ea7\u4eba\u6c11\u6cd5\u9662", "province": "\u5c71\u897f", "region": "\u6714\u5dde\u5e02", "leval": "3", "key": "001004006000"}, {"court": "\u5c71\u897f\u7701\u5ffb\u5dde\u5e02\u4e2d\u7ea7\u4eba\u6c11\u6cd5\u9662", "province": "\u5c71\u897f", "region": "\u5ffb\u5dde\u5e02", "leval": "3", "key": "001004008000"}, {"court": "\u5c71\u897f\u7701\u5415\u6881\u5e02\u4e2d\u7ea7\u4eba\u6c11\u6cd5\u9662", "province": "\u5c71\u897f", "region": "\u5415\u6881\u5e02", "leval": "3", "key": "001004009000"}, {"court": "\u5c71\u897f\u7701\u664b\u4e2d\u5e02\u4e2d\u7ea7\u4eba\u6c11\u6cd5\u9662", "province": "\u5c71\u897f", "region": "\u664b\u4e2d\u5e02", "leval": "3", "key": "001004010000"}, {"court": "\u5c71\u897f\u7701\u4e34\u6c7e\u5e02\u4e2d\u7ea7\u4eba\u6c11\u6cd5\u9662", "province": "\u5c71\u897f", "region": "\u4e34\u6c7e\u5e02", "leval": "3", "key": "001004011000"}, {"court": "\u5c71\u897f\u7701\u8fd0\u57ce\u5e02\u4e2d\u7ea7\u4eba\u6c11\u6cd5\u9662", "province": "\u5c71\u897f", "region": "\u8fd0\u57ce\u5e02", "leval": "3", "key": "001004012000"}, {"court": "\u592a\u539f\u94c1\u8def\u8fd0\u8f93\u4e2d\u7ea7\u6cd5\u9662", "province": "\u5c71\u897f", "region": "\u592a\u539f\u94c1\u8def\u8fd0\u8f93\u4e2d\u7ea7\u6cd5\u9662", "leval": "3", "key": "001004013000"}]